certify/__init__.py
certify/__main__.py
certify/certificate_transparency.py
certify/certify_class.py
certify/input_args.py
certify/misconfigurations/certificate_expiration.py
certify/misconfigurations/certificate_mismatched.py
certify/misconfigurations/certificate_revocation.py
certify/misconfigurations/certificate_self_signed.py
certify/misconfigurations/certificate_trust.py
certify/probes/alternative_names.py
certify/probes/calculate_hash.py
certify/probes/certificate_authority_verification.py
certify/probes/certificate_pinning.py
certify/probes/certificate_strength.py
certify/probes/common_name.py
certify/probes/jarm_hash.py
certify/probes/organization_name.py
certify/probes/serial_number.py
certify/probes/tls_version.py
certifycert-0.1.0.dist-info/LICENSE.md
certifycert-0.1.0.dist-info/METADATA
certifycert-0.1.0.dist-info/WHEEL
certifycert-0.1.0.dist-info/top_level.txt
certifycert-0.1.0.dist-info/RECORD
