Metadata-Version: 2.1
Name: certifycert
Version: 0.1.0
Summary: Certify is a python tool designed to check the security of SSL/TLS certificates.
Author-email: Shivam Saraswat <thecybersapien@protonmail.com>
License: MIT License
Project-URL: repository, https://github.com/shivamsaraswat/certify
Requires-Python: >=3.10
License-File: LICENSE.md
Requires-Dist: certifi
Requires-Dist: ocsp-checker
Requires-Dist: pyjarm
Requires-Dist: requests
Requires-Dist: pyopenssl
